xyz2png/__init__.py
xyz2png/main.py
xyz2png/py.typed
xyz2png-0.0.1.dist-info/LICENSE.txt
xyz2png-0.0.1.dist-info/METADATA
xyz2png-0.0.1.dist-info/WHEEL
xyz2png-0.0.1.dist-info/entry_points.txt
xyz2png-0.0.1.dist-info/RECORD
