Metadata-Version: 2.1
Name: xyz2png
Version: 0.0.1
Summary: Convert .xyz file into .png file
Home-page: https://github.com/eggplants/xyz2png
License: MIT
Author: eggplants
Author-email: w10776e8w@yahoo.co.jp
Requires-Python: >=3.9,<4.0
Classifier: License :: OSI Approved :: MIT License
Classifier: Programming Language :: Python :: 3
Classifier: Programming Language :: Python :: 3.9
Classifier: Programming Language :: Python :: 3.10
Classifier: Programming Language :: Python :: 3.11
Classifier: Programming Language :: Python :: 3.12
Requires-Dist: pillow (>=10.2.0,<11.0.0)
Requires-Dist: types-Pillow (>=10.2.0.20240324,<11.0.0.0)
Project-URL: Repository, https://github.com/eggplants/xyz2png
